redundantcss/__init__.py
redundantcss/redundantcss.py
redundantcss/validateArgs.py
redundantcss-0.0.3.dist-info/LICENSE
redundantcss-0.0.3.dist-info/METADATA
redundantcss-0.0.3.dist-info/WHEEL
redundantcss-0.0.3.dist-info/entry_points.txt
redundantcss-0.0.3.dist-info/top_level.txt
redundantcss-0.0.3.dist-info/RECORD
