Metadata-Version: 2.1
Name: redundantcss
Version: 0.0.3
Summary: Identifies redundant CSS classes not used by the templates provided.
Author: Josh Hofer
Author-email: <josh@securesap.com>
Project-URL: Source, https://github.com/JoshHofer01/RedundantCSS
Keywords: python,css,html,redundantcss,remove unused css
Classifier: Development Status :: 1 - Planning
Classifier: Intended Audience :: Developers
Classifier: Programming Language :: Python :: 3
Classifier: Natural Language :: English
Classifier: Operating System :: Unix
Classifier: Operating System :: MacOS :: MacOS X
Classifier: Operating System :: Microsoft :: Windows
License-File: LICENSE
Requires-Dist: beautifulsoup4
